winmutex/__init__.py
winmutex/__meta__.py
winmutex/handler.py
winmutex-1.0.1.dist-info/LICENSE
winmutex-1.0.1.dist-info/METADATA
winmutex-1.0.1.dist-info/WHEEL
winmutex-1.0.1.dist-info/RECORD
