Metadata-Version: 2.3
Name: winmutex
Version: 1.0.1
Summary: Simple handling mutexes with pywin32
License: MIT
Author: SantaSpeen
Author-email: santaspeen@gmail.com
Requires-Python: >=3.10,<4.0
Classifier: Development Status :: 5 - Production/Stable
Classifier: License :: OSI Approved :: MIT License
Classifier: Operating System :: Microsoft :: Windows
Classifier: Programming Language :: Python :: 3
Classifier: Programming Language :: Python :: 3.10
Classifier: Programming Language :: Python :: 3.11
Classifier: Programming Language :: Python :: 3.12
Classifier: Programming Language :: Python :: 3.13
Classifier: Topic :: Software Development :: Libraries :: Python Modules
Requires-Dist: pywin32 (>=310,<311)
Project-URL: Repository, https://github.com/SantaSpeen/winmutex
